{
  "default": {
    "buddhism": {
      "key": "buddhism",
      "name": "Buddhism",
      "photo": "https://firebasestorage.googleapis.com/v0/b/picon-co.appspot.com/o/religious%2Fbuddhism.jpeg?alt=media&token=474b3eb6-5c11-4eb0-a2eb-8732c203b1a0",
      "priority": 4
    },
    "christianity": {
      "key": "christianity",
      "name": "Christianity",
      "photo": "https://firebasestorage.googleapis.com/v0/b/picon-co.appspot.com/o/religious%2Fchristianity.jpeg?alt=media&token=aea36c00-558f-435d-b62a-a2717d90299a",
      "priority": 1
    },
    "ethnic": {
      "key": "ethnic",
      "name": "Ethnic",
      "photo": "https://firebasestorage.googleapis.com/v0/b/picon-co.appspot.com/o/religious%2Fethnic.jpeg?alt=media&token=931f1c8b-ff5b-40df-a36a-772e01d71441",
      "priority": 5
    },
    "hinduism": {
      "key": "hinduism",
      "name": "Hinduism",
      "photo": "https://firebasestorage.googleapis.com/v0/b/picon-co.appspot.com/o/religious%2Fhinduism.jpeg?alt=media&token=c851a807-e5b0-48b4-a330-51e233a91747",
      "priority": 3
    },
    "islam": {
      "key": "islam",
      "name": "Islam",
      "photo": "https://firebasestorage.googleapis.com/v0/b/picon-co.appspot.com/o/religious%2Fislam.jpeg?alt=media&token=779c5374-cf22-4b6e-a564-d094413802cf",
      "priority": 2
    },
    "other": {
      "key": "other",
      "name": "Other",
      "photo": "https://firebasestorage.googleapis.com/v0/b/picon-co.appspot.com/o/religious%2Fother.jpg?alt=media&token=76c6de55-fe00-4a93-b321-aa8c6f9b3be9",
      "priority": 6
    }
  }
}